Workbook

Sheet 1_Assumptions
A1: UTTARAKHAND ARTISAN MARKETPLACE — KEY ASSUMPTIONS (Year 1: Jul 2026 – Jun 2027)
A2: Blue cells = inputs you can change | Yellow background = key assumption
A3: A. REVENUE ASSUMPTIONS
A4: Commission rate (% of net GMV) | B4: 0.1 | C4: % | D4: 10% — lower than industry avg (15–18%) to keep artisans motivated
A5: Payment gateway fee (% of gross GMV) | B5: 0.02 | C5: % | D5: Razorpay/Cashfree standard rate; non-negotiable at this scale
A6: Returns & refunds rate | B6: 0.05 | C6: % | D6: 5% — handmade goods have quality variance; budget this or it surprises you
A7: Average Order Value Month 1 (₹) | B7: 650 | C7: ₹ | D7: ₹650 — realistic for craft impulse buys from unknown brand; NOT ₹2,000+
A8: AOV monthly increment (₹) | B8: 20 | C8: ₹ | D8: ₹20/month — as trust and higher-value items build; reaches ~₹870 by M12
A9: B. DEMAND ASSUMPTIONS
A10: Starting orders Month 1 | B10: 8 | C10: number | D10: 8 orders — friends, family, college network. Do NOT project 100+ at launch.
A11: Month-on-month order growth rate | B11: 0.15 | C11: % | D11: 15% MoM — aggressive but achievable with active social media; slows after M8
A12: Repeat purchase rate (% of customers) | B12: 0.1 | C12: % | D12: 10% reorder within 3 months — craft is low-frequency, don't over-model this
A13: C. ARTISAN & SUPPLY ASSUMPTIONS
A14: Total artisans onboarded (first trip) | B14: 30 | C14: number | D14: 30 artisans — 3 from each of 10 villages; onboarded in Month 1
A15: Villages covered | B15: 3 | C15: number | D15: Jaunsar, Chakrata, Munsiyari, Pithoragarh, Lansdowne + 5 more
A16: Artisans per village | B16: 10 | C16: number | D16: 3 per village — manageable trust-building; quality > quantity
A17: Active selling artisans (% of total) | B17: 0.6 | C17: % | D17: 60% active in any month — connectivity, stock, seasonal factors reduce this
A18: Products listed per active artisan | B18: 5 | C18: number | D18: 5 SKUs — teams list 20+ but cannot photograph/manage them. Be honest.
A19: New artisans added monthly (M2–M12) | B19: 2 | C19: number | D19: 2/month — 6 students with academic commitments; quality onboarding only
A20: D. VARIABLE COST ASSUMPTIONS (per order)
A21: Packaging cost per order (₹) | B21: 50 | C21: ₹ | D21: Kraft paper + branded sticker; students routinely forget this cost entirely
A22: Shipping subsidy per order (₹) | B22: 30 | C22: ₹ | D22: Customer pays shipping, you absorb ₹30 to stay competitive vs Amazon
A23: Customer support time cost per order (₹) | B23: 20 | C23: ₹ | D23: Proxy for team bandwidth cost; 10 min @ ₹120/hr student opportunity cost
A24: E. FIXED COST ASSUMPTIONS (monthly ₹)
A25: Website & hosting (₹/month) | B25: 2500 | C25: ₹ | D25: Shopify Starter or custom stack; use free tiers first, upgrade at Month 4+
A26: Marketing & social media (₹/month) | B26: 4000 | C26: ₹ | D26: Instagram reels + WhatsApp; no paid ads yet. ZERO budget = zero growth.
A27: Field travel — artisan visits (₹/month) | B27: 3000 | C27: ₹ | D27: Transport to villages for support visits, photo shoots, stock checks
A28: Miscellaneous & contingency (₹/month) | B28: 1500 | C28: ₹ | D28: Stationery, SIM, printing, unexpected. Always add 10–15% buffer.
A30: COLOUR KEY: Blue text = input (change these) | Yellow fill = key assumption | Green text = formula pulling from another sheet | Black text = calculated formula

Sheet 2_Artisans
A1: PART A — Monthly Cumulative Artisan Growth (Months 1–12)
A2: Month | B2: New Artisans Added | C2: Cumulative Artisans | D2: Active Artisans (60%) | E2: Total Products Listed
A3: Jul-26 | B3: ='1_Assumptions'!$B$14 -> 30 | C3: =B3 -> 30 | D3: =ROUND(C3*'1_Assumptions'!$B$17,0) -> 18 | E3: =D3*'1_Assumptions'!$B$18 -> 90
A4: Aug-26 | B4: ='1_Assumptions'!$B$19 -> 2 | C4: =C3+B4 -> 32 | D4: =ROUND(C4*'1_Assumptions'!$B$17,0) -> 19 | E4: =D4*'1_Assumptions'!$B$18 -> 95
A5: Sep-26 | B5: ='1_Assumptions'!$B$19 -> 2 | C5: =C4+B5 -> 34 | D5: =ROUND(C5*'1_Assumptions'!$B$17,0) -> 20 | E5: =D5*'1_Assumptions'!$B$18 -> 100
A6: Oct-26 | B6: ='1_Assumptions'!$B$19 -> 2 | C6: =C5+B6 -> 36 | D6: =ROUND(C6*'1_Assumptions'!$B$17,0) -> 22 | E6: =D6*'1_Assumptions'!$B$18 -> 110
A7: Nov-26 | B7: ='1_Assumptions'!$B$19 -> 2 | C7: =C6+B7 -> 38 | D7: =ROUND(C7*'1_Assumptions'!$B$17,0) -> 23 | E7: =D7*'1_Assumptions'!$B$18 -> 115
A8: Dec-26 | B8: ='1_Assumptions'!$B$19 -> 2 | C8: =C7+B8 -> 40 | D8: =ROUND(C8*'1_Assumptions'!$B$17,0) -> 24 | E8: =D8*'1_Assumptions'!$B$18 -> 120
A9: Jan-27 | B9: ='1_Assumptions'!$B$19 -> 2 | C9: =C8+B9 -> 42 | D9: =ROUND(C9*'1_Assumptions'!$B$17,0) -> 25 | E9: =D9*'1_Assumptions'!$B$18 -> 125
A10: Feb-27 | B10: ='1_Assumptions'!$B$19 -> 2 | C10: =C9+B10 -> 44 | D10: =ROUND(C10*'1_Assumptions'!$B$17,0) -> 26 | E10: =D10*'1_Assumptions'!$B$18 -> 130
A11: Mar-27 | B11: ='1_Assumptions'!$B$19 -> 2 | C11: =C10+B11 -> 46 | D11: =ROUND(C11*'1_Assumptions'!$B$17,0) -> 28 | E11: =D11*'1_Assumptions'!$B$18 -> 140
A12: Apr-27 | B12: ='1_Assumptions'!$B$19 -> 2 | C12: =C11+B12 -> 48 | D12: =ROUND(C12*'1_Assumptions'!$B$17,0) -> 29 | E12: =D12*'1_Assumptions'!$B$18 -> 145
A13: May-27 | B13: ='1_Assumptions'!$B$19 -> 2 | C13: =C12+B13 -> 50 | D13: =ROUND(C13*'1_Assumptions'!$B$17,0) -> 30 | E13: =D13*'1_Assumptions'!$B$18 -> 150
A14: Jun-27 | B14: ='1_Assumptions'!$B$19 -> 2 | C14: =C13+B14 -> 52 | D14: =ROUND(C14*'1_Assumptions'!$B$17,0) -> 31 | E14: =D14*'1_Assumptions'!$B$18 -> 155

Sheet 3_Demand
A1: DEMAND MODEL — ORDERS, AOV, GMV (Month by Month)
A2: Line Item | B2: Jul-26 | C2: Aug-26 | D2: Sep-26 | E2: Oct-26 | F2: Nov-26 | G2: Dec-26 | H2: Jan-27 | I2: Feb-27 | J2: Mar-27 | K2: Apr-27 | L2: May-27 | M2: Jun-27 | N2: Year 1 Total
A3: Orders (gross)
A4: Estimated orders | B4: ='1_Assumptions'!$B$10 -> 8 | C4: =ROUND(B4*(1+'1_Assumptions'!$B$11),0) -> 9 | D4: =ROUND(C4*(1+'1_Assumptions'!$B$11),0) -> 10 | E4: =ROUND(D4*(1+'1_Assumptions'!$B$11),0) -> 12 | F4: =ROUND(E4*(1+'1_Assumptions'!$B$11),0) -> 14 | G4: =ROUND(F4*(1+'1_Assumptions'!$B$11),0) -> 16 | H4: =ROUND(G4*(1+'1_Assumptions'!$B$11),0) -> 18 | I4: =ROUND(H4*(1+'1_Assumptions'!$B$11),0) -> 21 | J4: =ROUND(I4*(1+'1_Assumptions'!$B$11),0) -> 24 | ... M4: =ROUND(L4*(1+'1_Assumptions'!$B$11),0) -> 37 | N4: =SUM(B4:M4) -> 229
A5: Returns & cancellations | B5: =-ROUND(B4*'1_Assumptions'!$B$6,0) -> 0 | C5: =-ROUND(C4*'1_Assumptions'!$B$6,0) -> 0 | D5: =-ROUND(D4*'1_Assumptions'!$B$6,0) -> -1 | E5: =-ROUND(E4*'1_Assumptions'!$B$6,0) -> -1 | F5: =-ROUND(F4*'1_Assumptions'!$B$6,0) -> -1 | G5: =-ROUND(G4*'1_Assumptions'!$B$6,0) -> -1 | H5: =-ROUND(H4*'1_Assumptions'!$B$6,0) -> -1 | I5: =-ROUND(I4*'1_Assumptions'!$B$6,0) -> -1 | ... M5: =-ROUND(M4*'1_Assumptions'!$B$6,0) -> -2 | N5: =SUM(B5:M5) -> -12
A6: Net orders fulfilled | B6: =B4+B5 -> 8 | C6: =C4+C5 -> 9 | D6: =D4+D5 -> 9 | E6: =E4+E5 -> 11 | F6: =F4+F5 -> 13 | G6: =G4+G5 -> 15 | H6: =H4+H5 -> 17 | I6: =I4+I5 -> 20 | ... M6: =M4+M5 -> 35 | N6: =SUM(B6:M6) -> 217
A7: Average Order Value (₹)
A8: AOV (₹) | B8: ='1_Assumptions'!$B$7 -> 650 | C8: =B8+'1_Assumptions'!$B$8 -> 670 | D8: =C8+'1_Assumptions'!$B$8 -> 690 | E8: =D8+'1_Assumptions'!$B$8 -> 710 | F8: =E8+'1_Assumptions'!$B$8 -> 730 | G8: =F8+'1_Assumptions'!$B$8 -> 750 | H8: =G8+'1_Assumptions'!$B$8 -> 770 | I8: =H8+'1_Assumptions'!$B$8 -> 790 | J8: =I8+'1_Assumptions'!$B$8 -> 810 | ... M8: =L8+'1_Assumptions'!$B$8 -> 870 | N8: =AVERAGE(B8:M8) -> 760
A9: GMV
A10: Gross GMV (₹) | B10: =B4*B8 -> 5200 | C10: =C4*C8 -> 6030 | D10: =D4*D8 -> 6900 | E10: =E4*E8 -> 8520 | F10: =F4*F8 -> 10220 | G10: =G4*G8 -> 12000 | H10: =H4*H8 -> 13860 | I10: =I4*I8 -> 16590 | ... M10: =M4*M8 -> 32190 | N10: =SUM(B10:M10) -> 181390
A11: Net GMV after returns (₹) | B11: =B6*B8 -> 5200 | C11: =C6*C8 -> 6030 | D11: =D6*D8 -> 6210 | E11: =E6*E8 -> 7810 | F11: =F6*F8 -> 9490 | G11: =G6*G8 -> 11250 | H11: =H6*H8 -> 13090 | I11: =I6*I8 -> 15800 | ... M11: =M6*M8 -> 30450 | N11: =SUM(B11:M11) -> 171870

Sheet 4_Costs
A1: COST MODEL — VARIABLE & FIXED COSTS (Month by Month)
A2: Cost Line | B2: Jul-26 | C2: Aug-26 | D2: Sep-26 | E2: Oct-26 | F2: Nov-26 | G2: Dec-26 | H2: Jan-27 | I2: Feb-27 | J2: Mar-27 | K2: Apr-27 | L2: May-27 | M2: Jun-27 | N2: Year 1 Total
A3: VARIABLE COSTS
A4: Payment gateway fee (2% of GMV) | B4: ='3_Demand'!B11*'1_Assumptions'!$B$5 -> 104 | C4: ='3_Demand'!C11*'1_Assumptions'!$B$5 -> 120.6 | D4: ='3_Demand'!D11*'1_Assumptions'!$B$5 -> 124.2 | E4: ='3_Demand'!E11*'1_Assumptions'!$B$5 -> 156.2 | F4: ='3_Demand'!F11*'1_Assumptions'!$B$5 -> 189.8 | G4: ='3_Demand'!G11*'1_Assumptions'!$B$5 -> 225 | H4: ='3_Demand'!H11*'1_Assumptions'!$B$5 -> 261.8 | I4: ='3_Demand'!I11*'1_Assumptions'!$B$5 -> 316 | ... M4: ='3_Demand'!M11*'1_Assumptions'!$B$5 -> 609 | N4: =SUM(B4:M4) -> 3437.4
A5: Packaging materials (₹50/order) | B5: ='3_Demand'!B6*'1_Assumptions'!$B$21 -> 400 | C5: ='3_Demand'!C6*'1_Assumptions'!$B$21 -> 450 | D5: ='3_Demand'!D6*'1_Assumptions'!$B$21 -> 450 | E5: ='3_Demand'!E6*'1_Assumptions'!$B$21 -> 550 | F5: ='3_Demand'!F6*'1_Assumptions'!$B$21 -> 650 | G5: ='3_Demand'!G6*'1_Assumptions'!$B$21 -> 750 | H5: ='3_Demand'!H6*'1_Assumptions'!$B$21 -> 850 | I5: ='3_Demand'!I6*'1_Assumptions'!$B$21 -> 1000 | ... M5: ='3_Demand'!M6*'1_Assumptions'!$B$21 -> 1750 | N5: =SUM(B5:M5) -> 10850
A6: Shipping subsidy (₹30/order) | B6: ='3_Demand'!B6*'1_Assumptions'!$B$22 -> 240 | C6: ='3_Demand'!C6*'1_Assumptions'!$B$22 -> 270 | D6: ='3_Demand'!D6*'1_Assumptions'!$B$22 -> 270 | E6: ='3_Demand'!E6*'1_Assumptions'!$B$22 -> 330 | F6: ='3_Demand'!F6*'1_Assumptions'!$B$22 -> 390 | G6: ='3_Demand'!G6*'1_Assumptions'!$B$22 -> 450 | H6: ='3_Demand'!H6*'1_Assumptions'!$B$22 -> 510 | I6: ='3_Demand'!I6*'1_Assumptions'!$B$22 -> 600 | ... M6: ='3_Demand'!M6*'1_Assumptions'!$B$22 -> 1050 | N6: =SUM(B6:M6) -> 6510
A7: Customer support cost (₹20/order) | B7: ='3_Demand'!B6*'1_Assumptions'!$B$23 -> 160 | C7: ='3_Demand'!C6*'1_Assumptions'!$B$23 -> 180 | D7: ='3_Demand'!D6*'1_Assumptions'!$B$23 -> 180 | E7: ='3_Demand'!E6*'1_Assumptions'!$B$23 -> 220 | F7: ='3_Demand'!F6*'1_Assumptions'!$B$23 -> 260 | G7: ='3_Demand'!G6*'1_Assumptions'!$B$23 -> 300 | H7: ='3_Demand'!H6*'1_Assumptions'!$B$23 -> 340 | I7: ='3_Demand'!I6*'1_Assumptions'!$B$23 -> 400 | ... M7: ='3_Demand'!M6*'1_Assumptions'!$B$23 -> 700 | N7: =SUM(B7:M7) -> 4340
A8: TOTAL VARIABLE COSTS | B8: =B4+B5+B6+B7 -> 904 | C8: =C4+C5+C6+C7 -> 1020.6 | D8: =D4+D5+D6+D7 -> 1024.2 | E8: =E4+E5+E6+E7 -> 1256.2 | F8: =F4+F5+F6+F7 -> 1489.8 | G8: =G4+G5+G6+G7 -> 1725 | H8: =H4+H5+H6+H7 -> 1961.8 | I8: =I4+I5+I6+I7 -> 2316 | ... M8: =M4+M5+M6+M7 -> 4109 | N8: =SUM(B8:M8) -> 25137.4
A9: FIXED COSTS
A10: Website & hosting | B10: ='1_Assumptions'!$B$25 -> 2500 | C10: ='1_Assumptions'!$B$25 -> 2500 | D10: ='1_Assumptions'!$B$25 -> 2500 | E10: ='1_Assumptions'!$B$25 -> 2500 | F10: ='1_Assumptions'!$B$25 -> 2500 | G10: ='1_Assumptions'!$B$25 -> 2500 | H10: ='1_Assumptions'!$B$25 -> 2500 | I10: ='1_Assumptions'!$B$25 -> 2500 | ... M10: ='1_Assumptions'!$B$25 -> 2500 | N10: =SUM(B10:M10) -> 30000
A11: Marketing & social media | B11: ='1_Assumptions'!$B$26 -> 4000 | C11: ='1_Assumptions'!$B$26 -> 4000 | D11: ='1_Assumptions'!$B$26 -> 4000 | E11: ='1_Assumptions'!$B$26 -> 4000 | F11: ='1_Assumptions'!$B$26 -> 4000 | G11: ='1_Assumptions'!$B$26 -> 4000 | H11: ='1_Assumptions'!$B$26 -> 4000 | I11: ='1_Assumptions'!$B$26 -> 4000 | ... M11: ='1_Assumptions'!$B$26 -> 4000 | N11: =SUM(B11:M11) -> 48000
A12: Field travel — artisan visits | B12: ='1_Assumptions'!$B$27 -> 3000 | C12: ='1_Assumptions'!$B$27 -> 3000 | D12: ='1_Assumptions'!$B$27 -> 3000 | E12: ='1_Assumptions'!$B$27 -> 3000 | F12: ='1_Assumptions'!$B$27 -> 3000 | G12: ='1_Assumptions'!$B$27 -> 3000 | H12: ='1_Assumptions'!$B$27 -> 3000 | I12: ='1_Assumptions'!$B$27 -> 3000 | ... M12: ='1_Assumptions'!$B$27 -> 3000 | N12: =SUM(B12:M12) -> 36000
A13: Miscellaneous & contingency | B13: ='1_Assumptions'!$B$28 -> 1500 | C13: ='1_Assumptions'!$B$28 -> 1500 | D13: ='1_Assumptions'!$B$28 -> 1500 | E13: ='1_Assumptions'!$B$28 -> 1500 | F13: ='1_Assumptions'!$B$28 -> 1500 | G13: ='1_Assumptions'!$B$28 -> 1500 | H13: ='1_Assumptions'!$B$28 -> 1500 | I13: ='1_Assumptions'!$B$28 -> 1500 | ... M13: ='1_Assumptions'!$B$28 -> 1500 | N13: =SUM(B13:M13) -> 18000
A14: TOTAL FIXED COSTS | B14: =B10+B11+B12+B13 -> 11000 | C14: =C10+C11+C12+C13 -> 11000 | D14: =D10+D11+D12+D13 -> 11000 | E14: =E10+E11+E12+E13 -> 11000 | F14: =F10+F11+F12+F13 -> 11000 | G14: =G10+G11+G12+G13 -> 11000 | H14: =H10+H11+H12+H13 -> 11000 | I14: =I10+I11+I12+I13 -> 11000 | ... M14: =M10+M11+M12+M13 -> 11000 | N14: =SUM(B14:M14) -> 132000
A15: TOTAL COSTS | B15: =B8+B14 -> 11904 | C15: =C8+C14 -> 12020.6 | D15: =D8+D14 -> 12024.2 | E15: =E8+E14 -> 12256.2 | F15: =F8+F14 -> 12489.8 | G15: =G8+G14 -> 12725 | H15: =H8+H14 -> 12961.8 | I15: =I8+I14 -> 13316 | ... M15: =M8+M14 -> 15109 | N15: =SUM(B15:M15) -> 157137.4

Sheet 5_P&L
A1: PROFIT & LOSS STATEMENT — MONTH BY MONTH (₹)
A2: Line Item | B2: Jul-26 | C2: Aug-26 | D2: Sep-26 | E2: Oct-26 | F2: Nov-26 | G2: Dec-26 | H2: Jan-27 | I2: Feb-27 | J2: Mar-27 | K2: Apr-27 | L2: May-27 | M2: Jun-27 | N2: Year 1 Total
A3: REVENUE
A4: Gross GMV | B4: ='3_Demand'!B10 -> 5200 | C4: ='3_Demand'!C10 -> 6030 | D4: ='3_Demand'!D10 -> 6900 | E4: ='3_Demand'!E10 -> 8520 | F4: ='3_Demand'!F10 -> 10220 | G4: ='3_Demand'!G10 -> 12000 | H4: ='3_Demand'!H10 -> 13860 | I4: ='3_Demand'!I10 -> 16590 | ... M4: ='3_Demand'!M10 -> 32190 | N4: =SUM(B4:M4) -> 181390
A5: Less: Returns | B5: ='3_Demand'!B5 -> 0 | C5: ='3_Demand'!C5 -> 0 | D5: ='3_Demand'!D5 -> -1 | E5: ='3_Demand'!E5 -> -1 | F5: ='3_Demand'!F5 -> -1 | G5: ='3_Demand'!G5 -> -1 | H5: ='3_Demand'!H5 -> -1 | I5: ='3_Demand'!I5 -> -1 | ... M5: ='3_Demand'!M5 -> -2 | N5: =SUM(B5:M5) -> -12
A6: Net GMV | B6: ='3_Demand'!B11 -> 5200 | C6: ='3_Demand'!C11 -> 6030 | D6: ='3_Demand'!D11 -> 6210 | E6: ='3_Demand'!E11 -> 7810 | F6: ='3_Demand'!F11 -> 9490 | G6: ='3_Demand'!G11 -> 11250 | H6: ='3_Demand'!H11 -> 13090 | I6: ='3_Demand'!I11 -> 15800 | ... M6: ='3_Demand'!M11 -> 30450 | N6: =SUM(B6:M6) -> 171870
A7: Platform commission (10%) | B7: ='3_Demand'!B11*'1_Assumptions'!$B$4 -> 520 | C7: ='3_Demand'!C11*'1_Assumptions'!$B$4 -> 603 | D7: ='3_Demand'!D11*'1_Assumptions'!$B$4 -> 621 | E7: ='3_Demand'!E11*'1_Assumptions'!$B$4 -> 781 | F7: ='3_Demand'!F11*'1_Assumptions'!$B$4 -> 949 | G7: ='3_Demand'!G11*'1_Assumptions'!$B$4 -> 1125 | H7: ='3_Demand'!H11*'1_Assumptions'!$B$4 -> 1309 | I7: ='3_Demand'!I11*'1_Assumptions'!$B$4 -> 1580 | ... M7: ='3_Demand'!M11*'1_Assumptions'!$B$4 -> 3045 | N7: =SUM(B7:M7) -> 17187
A8: VARIABLE COSTS
A9: Payment gateway fee | B9: ='4_Costs'!B4 -> 104 | C9: ='4_Costs'!C4 -> 120.6 | D9: ='4_Costs'!D4 -> 124.2 | E9: ='4_Costs'!E4 -> 156.2 | F9: ='4_Costs'!F4 -> 189.8 | G9: ='4_Costs'!G4 -> 225 | H9: ='4_Costs'!H4 -> 261.8 | I9: ='4_Costs'!I4 -> 316 | ... M9: ='4_Costs'!M4 -> 609 | N9: =SUM(B9:M9) -> 3437.4
A10: Packaging | B10: ='4_Costs'!B5 -> 400 | C10: ='4_Costs'!C5 -> 450 | D10: ='4_Costs'!D5 -> 450 | E10: ='4_Costs'!E5 -> 550 | F10: ='4_Costs'!F5 -> 650 | G10: ='4_Costs'!G5 -> 750 | H10: ='4_Costs'!H5 -> 850 | I10: ='4_Costs'!I5 -> 1000 | ... M10: ='4_Costs'!M5 -> 1750 | N10: =SUM(B10:M10) -> 10850
A11: Shipping subsidy | B11: ='4_Costs'!B6 -> 240 | C11: ='4_Costs'!C6 -> 270 | D11: ='4_Costs'!D6 -> 270 | E11: ='4_Costs'!E6 -> 330 | F11: ='4_Costs'!F6 -> 390 | G11: ='4_Costs'!G6 -> 450 | H11: ='4_Costs'!H6 -> 510 | I11: ='4_Costs'!I6 -> 600 | ... M11: ='4_Costs'!M6 -> 1050 | N11: =SUM(B11:M11) -> 6510
A12: Customer support | B12: ='4_Costs'!B7 -> 160 | C12: ='4_Costs'!C7 -> 180 | D12: ='4_Costs'!D7 -> 180 | E12: ='4_Costs'!E7 -> 220 | F12: ='4_Costs'!F7 -> 260 | G12: ='4_Costs'!G7 -> 300 | H12: ='4_Costs'!H7 -> 340 | I12: ='4_Costs'!I7 -> 400 | ... M12: ='4_Costs'!M7 -> 700 | N12: =SUM(B12:M12) -> 4340
A13: Total variable costs | B13: ='4_Costs'!B8 -> 904 | C13: ='4_Costs'!C8 -> 1020.6 | D13: ='4_Costs'!D8 -> 1024.2 | E13: ='4_Costs'!E8 -> 1256.2 | F13: ='4_Costs'!F8 -> 1489.8 | G13: ='4_Costs'!G8 -> 1725 | H13: ='4_Costs'!H8 -> 1961.8 | I13: ='4_Costs'!I8 -> 2316 | ... M13: ='4_Costs'!M8 -> 4109 | N13: =SUM(B13:M13) -> 25137.4
A14: CONTRIBUTION MARGIN | B14: =B7-B13 -> -384 | C14: =C7-C13 -> -417.6 | D14: =D7-D13 -> -403.2 | E14: =E7-E13 -> -475.2 | F14: =F7-F13 -> -540.8 | G14: =G7-G13 -> -600 | H14: =H7-H13 -> -652.8 | I14: =I7-I13 -> -736 | ... M14: =M7-M13 -> -1064 | N14: =SUM(B14:M14) -> -7950.4
A15: Contribution margin % | B15: =IFERROR(B14/B7,0) -> -0.73846154 | C15: =IFERROR(C14/C7,0) -> -0.69253731 | D15: =IFERROR(D14/D7,0) -> -0.64927536 | E15: =IFERROR(E14/E7,0) -> -0.6084507 | F15: =IFERROR(F14/F7,0) -> -0.56986301 | G15: =IFERROR(G14/G7,0) -> -0.53333333 | H15: =IFERROR(H14/H7,0) -> -0.4987013 | I15: =IFERROR(I14/I7,0) -> -0.46582278 | ... M15: =IFERROR(M14/M7,0) -> -0.34942529 | N15: =AVERAGE(B15:M15) -> -0.5268107
A16: FIXED COSTS
A17: Website & hosting | B17: ='4_Costs'!B10 -> 2500 | C17: ='4_Costs'!C10 -> 2500 | D17: ='4_Costs'!D10 -> 2500 | E17: ='4_Costs'!E10 -> 2500 | F17: ='4_Costs'!F10 -> 2500 | G17: ='4_Costs'!G10 -> 2500 | H17: ='4_Costs'!H10 -> 2500 | I17: ='4_Costs'!I10 -> 2500 | ... M17: ='4_Costs'!M10 -> 2500 | N17: =SUM(B17:M17) -> 30000
A18: Marketing | B18: ='4_Costs'!B11 -> 4000 | C18: ='4_Costs'!C11 -> 4000 | D18: ='4_Costs'!D11 -> 4000 | E18: ='4_Costs'!E11 -> 4000 | F18: ='4_Costs'!F11 -> 4000 | G18: ='4_Costs'!G11 -> 4000 | H18: ='4_Costs'!H11 -> 4000 | I18: ='4_Costs'!I11 -> 4000 | ... M18: ='4_Costs'!M11 -> 4000 | N18: =SUM(B18:M18) -> 48000
A19: Field travel | B19: ='4_Costs'!B12 -> 3000 | C19: ='4_Costs'!C12 -> 3000 | D19: ='4_Costs'!D12 -> 3000 | E19: ='4_Costs'!E12 -> 3000 | F19: ='4_Costs'!F12 -> 3000 | G19: ='4_Costs'!G12 -> 3000 | H19: ='4_Costs'!H12 -> 3000 | I19: ='4_Costs'!I12 -> 3000 | ... M19: ='4_Costs'!M12 -> 3000 | N19: =SUM(B19:M19) -> 36000
A20: Miscellaneous | B20: ='4_Costs'!B13 -> 1500 | C20: ='4_Costs'!C13 -> 1500 | D20: ='4_Costs'!D13 -> 1500 | E20: ='4_Costs'!E13 -> 1500 | F20: ='4_Costs'!F13 -> 1500 | G20: ='4_Costs'!G13 -> 1500 | H20: ='4_Costs'!H13 -> 1500 | I20: ='4_Costs'!I13 -> 1500 | ... M20: ='4_Costs'!M13 -> 1500 | N20: =SUM(B20:M20) -> 18000
A21: Total fixed costs | B21: ='4_Costs'!B14 -> 11000 | C21: ='4_Costs'!C14 -> 11000 | D21: ='4_Costs'!D14 -> 11000 | E21: ='4_Costs'!E14 -> 11000 | F21: ='4_Costs'!F14 -> 11000 | G21: ='4_Costs'!G14 -> 11000 | H21: ='4_Costs'!H14 -> 11000 | I21: ='4_Costs'!I14 -> 11000 | ... M21: ='4_Costs'!M14 -> 11000 | N21: =SUM(B21:M21) -> 132000
A22: NET PROFIT / (LOSS) | B22: =B14-B21 -> -11384 | C22: =C14-C21 -> -11417.6 | D22: =D14-D21 -> -11403.2 | E22: =E14-E21 -> -11475.2 | F22: =F14-F21 -> -11540.8 | G22: =G14-G21 -> -11600 | H22: =H14-H21 -> -11652.8 | I22: =I14-I21 -> -11736 | ... M22: =M14-M21 -> -12064 | N22: =SUM(B22:M22) -> -139950.4
A23: Cumulative P&L | B23: =B22 -> -11384 | C23: =B23+C22 -> -22801.6 | D23: =C23+D22 -> -34204.8 | E23: =D23+E22 -> -45680 | F23: =E23+F22 -> -57220.8 | G23: =F23+G22 -> -68820.8 | H23: =G23+H22 -> -80473.6 | I23: =H23+I22 -> -92209.6 | J23: =I23+J22 -> -104019.2 | ... M23: =L23+M22 -> -139950.4
A24: Break-even orders needed | B24: =IFERROR(ROUND(B21/IFERROR(B14/'3_Demand'!B6,0),0),"-") -> -229 | C24: =IFERROR(ROUND(C21/IFERROR(C14/'3_Demand'!C6,0),0),"-") -> -237 | D24: =IFERROR(ROUND(D21/IFERROR(D14/'3_Demand'!D6,0),0),"-") -> -246 | E24: =IFERROR(ROUND(E21/IFERROR(E14/'3_Demand'!E6,0),0),"-") -> -255 | F24: =IFERROR(ROUND(F21/IFERROR(F14/'3_Demand'!F6,0),0),"-") -> -264 | G24: =IFERROR(ROUND(G21/IFERROR(G14/'3_Demand'!G6,0),0),"-") -> -275 | H24: =IFERROR(ROUND(H21/IFERROR(H14/'3_Demand'!H6,0),0),"-") -> -286 | I24: =IFERROR(ROUND(I21/IFERROR(I14/'3_Demand'!I6,0),0),"-") -> -299 | ... M24: =IFERROR(ROUND(M21/IFERROR(M14/'3_Demand'!M6,0),0),"-") -> -362

Sheet 6_UnitEconomics
A1: UNIT ECONOMICS — PER ORDER ANALYSIS (Month by Month)
A2: Metric | B2: Jul-26 | C2: Aug-26 | D2: Sep-26 | E2: Oct-26 | F2: Nov-26 | G2: Dec-26 | H2: Jan-27 | I2: Feb-27 | J2: Mar-27 | K2: Apr-27 | L2: May-27 | M2: Jun-27 | N2: Avg / Year
A3: Orders (net fulfilled) | B3: ='3_Demand'!B6 -> 8 | C3: ='3_Demand'!C6 -> 9 | D3: ='3_Demand'!D6 -> 9 | E3: ='3_Demand'!E6 -> 11 | F3: ='3_Demand'!F6 -> 13 | G3: ='3_Demand'!G6 -> 15 | H3: ='3_Demand'!H6 -> 17 | I3: ='3_Demand'!I6 -> 20 | ... M3: ='3_Demand'!M6 -> 35 | N3: =AVERAGE(B3:M3) -> 18.083333
A4: Revenue per order (₹) | B4: =IFERROR('5_P&L'!B7/'3_Demand'!B6,0) -> 65 | C4: =IFERROR('5_P&L'!C7/'3_Demand'!C6,0) -> 67 | D4: =IFERROR('5_P&L'!D7/'3_Demand'!D6,0) -> 69 | E4: =IFERROR('5_P&L'!E7/'3_Demand'!E6,0) -> 71 | F4: =IFERROR('5_P&L'!F7/'3_Demand'!F6,0) -> 73 | G4: =IFERROR('5_P&L'!G7/'3_Demand'!G6,0) -> 75 | H4: =IFERROR('5_P&L'!H7/'3_Demand'!H6,0) -> 77 | I4: =IFERROR('5_P&L'!I7/'3_Demand'!I6,0) -> 79 | ... M4: =IFERROR('5_P&L'!M7/'3_Demand'!M6,0) -> 87 | N4: =AVERAGE(B4:M4) -> 76
A5: Variable cost per order (₹) | B5: =IFERROR('5_P&L'!B13/'3_Demand'!B6,0) -> 113 | C5: =IFERROR('5_P&L'!C13/'3_Demand'!C6,0) -> 113.4 | D5: =IFERROR('5_P&L'!D13/'3_Demand'!D6,0) -> 113.8 | E5: =IFERROR('5_P&L'!E13/'3_Demand'!E6,0) -> 114.2 | F5: =IFERROR('5_P&L'!F13/'3_Demand'!F6,0) -> 114.6 | G5: =IFERROR('5_P&L'!G13/'3_Demand'!G6,0) -> 115 | H5: =IFERROR('5_P&L'!H13/'3_Demand'!H6,0) -> 115.4 | I5: =IFERROR('5_P&L'!I13/'3_Demand'!I6,0) -> 115.8 | ... M5: =IFERROR('5_P&L'!M13/'3_Demand'!M6,0) -> 117.4 | N5: =AVERAGE(B5:M5) -> 115.2
A6: of which: gateway fee | B6: =IFERROR('4_Costs'!B4/'3_Demand'!B6,0) -> 13 | C6: =IFERROR('4_Costs'!C4/'3_Demand'!C6,0) -> 13.4 | D6: =IFERROR('4_Costs'!D4/'3_Demand'!D6,0) -> 13.8 | E6: =IFERROR('4_Costs'!E4/'3_Demand'!E6,0) -> 14.2 | F6: =IFERROR('4_Costs'!F4/'3_Demand'!F6,0) -> 14.6 | G6: =IFERROR('4_Costs'!G4/'3_Demand'!G6,0) -> 15 | H6: =IFERROR('4_Costs'!H4/'3_Demand'!H6,0) -> 15.4 | I6: =IFERROR('4_Costs'!I4/'3_Demand'!I6,0) -> 15.8 | ... M6: =IFERROR('4_Costs'!M4/'3_Demand'!M6,0) -> 17.4 | N6: =AVERAGE(B6:M6) -> 15.2
A7: of which: packaging | B7: =IFERROR('4_Costs'!B5/'3_Demand'!B6,0) -> 50 | C7: =IFERROR('4_Costs'!C5/'3_Demand'!C6,0) -> 50 | D7: =IFERROR('4_Costs'!D5/'3_Demand'!D6,0) -> 50 | E7: =IFERROR('4_Costs'!E5/'3_Demand'!E6,0) -> 50 | F7: =IFERROR('4_Costs'!F5/'3_Demand'!F6,0) -> 50 | G7: =IFERROR('4_Costs'!G5/'3_Demand'!G6,0) -> 50 | H7: =IFERROR('4_Costs'!H5/'3_Demand'!H6,0) -> 50 | I7: =IFERROR('4_Costs'!I5/'3_Demand'!I6,0) -> 50 | ... M7: =IFERROR('4_Costs'!M5/'3_Demand'!M6,0) -> 50 | N7: =AVERAGE(B7:M7) -> 50
A8: of which: shipping | B8: =IFERROR('4_Costs'!B6/'3_Demand'!B6,0) -> 30 | C8: =IFERROR('4_Costs'!C6/'3_Demand'!C6,0) -> 30 | D8: =IFERROR('4_Costs'!D6/'3_Demand'!D6,0) -> 30 | E8: =IFERROR('4_Costs'!E6/'3_Demand'!E6,0) -> 30 | F8: =IFERROR('4_Costs'!F6/'3_Demand'!F6,0) -> 30 | G8: =IFERROR('4_Costs'!G6/'3_Demand'!G6,0) -> 30 | H8: =IFERROR('4_Costs'!H6/'3_Demand'!H6,0) -> 30 | I8: =IFERROR('4_Costs'!I6/'3_Demand'!I6,0) -> 30 | ... M8: =IFERROR('4_Costs'!M6/'3_Demand'!M6,0) -> 30 | N8: =AVERAGE(B8:M8) -> 30
A9: of which: support | B9: =IFERROR('4_Costs'!B7/'3_Demand'!B6,0) -> 20 | C9: =IFERROR('4_Costs'!C7/'3_Demand'!C6,0) -> 20 | D9: =IFERROR('4_Costs'!D7/'3_Demand'!D6,0) -> 20 | E9: =IFERROR('4_Costs'!E7/'3_Demand'!E6,0) -> 20 | F9: =IFERROR('4_Costs'!F7/'3_Demand'!F6,0) -> 20 | G9: =IFERROR('4_Costs'!G7/'3_Demand'!G6,0) -> 20 | H9: =IFERROR('4_Costs'!H7/'3_Demand'!H6,0) -> 20 | I9: =IFERROR('4_Costs'!I7/'3_Demand'!I6,0) -> 20 | ... M9: =IFERROR('4_Costs'!M7/'3_Demand'!M6,0) -> 20 | N9: =AVERAGE(B9:M9) -> 20
A10: Contribution per order (₹) | B10: =IFERROR('5_P&L'!B14/'3_Demand'!B6,0) -> -48 | C10: =IFERROR('5_P&L'!C14/'3_Demand'!C6,0) -> -46.4 | D10: =IFERROR('5_P&L'!D14/'3_Demand'!D6,0) -> -44.8 | E10: =IFERROR('5_P&L'!E14/'3_Demand'!E6,0) -> -43.2 | F10: =IFERROR('5_P&L'!F14/'3_Demand'!F6,0) -> -41.6 | G10: =IFERROR('5_P&L'!G14/'3_Demand'!G6,0) -> -40 | H10: =IFERROR('5_P&L'!H14/'3_Demand'!H6,0) -> -38.4 | I10: =IFERROR('5_P&L'!I14/'3_Demand'!I6,0) -> -36.8 | ... M10: =IFERROR('5_P&L'!M14/'3_Demand'!M6,0) -> -30.4 | N10: =AVERAGE(B10:M10) -> -39.2
A11: Contribution margin % | B11: =IFERROR('5_P&L'!B14/'5_P&L'!B7,0) -> -0.73846154 | C11: =IFERROR('5_P&L'!C14/'5_P&L'!C7,0) -> -0.69253731 | D11: =IFERROR('5_P&L'!D14/'5_P&L'!D7,0) -> -0.64927536 | E11: =IFERROR('5_P&L'!E14/'5_P&L'!E7,0) -> -0.6084507 | F11: =IFERROR('5_P&L'!F14/'5_P&L'!F7,0) -> -0.56986301 | G11: =IFERROR('5_P&L'!G14/'5_P&L'!G7,0) -> -0.53333333 | H11: =IFERROR('5_P&L'!H14/'5_P&L'!H7,0) -> -0.4987013 | I11: =IFERROR('5_P&L'!I14/'5_P&L'!I7,0) -> -0.46582278 | ... M11: =IFERROR('5_P&L'!M14/'5_P&L'!M7,0) -> -0.34942529 | N11: =AVERAGE(B11:M11) -> -0.5268107
A12: Break-even orders needed/month | B12: =IFERROR(ROUND('5_P&L'!B19/IFERROR('5_P&L'!B14/'3_Demand'!B6,1),0),0) -> -63 | C12: =IFERROR(ROUND('5_P&L'!C19/IFERROR('5_P&L'!C14/'3_Demand'!C6,1),0),0) -> -65 | D12: =IFERROR(ROUND('5_P&L'!D19/IFERROR('5_P&L'!D14/'3_Demand'!D6,1),0),0) -> -67 | E12: =IFERROR(ROUND('5_P&L'!E19/IFERROR('5_P&L'!E14/'3_Demand'!E6,1),0),0) -> -69 | F12: =IFERROR(ROUND('5_P&L'!F19/IFERROR('5_P&L'!F14/'3_Demand'!F6,1),0),0) -> -72 | G12: =IFERROR(ROUND('5_P&L'!G19/IFERROR('5_P&L'!G14/'3_Demand'!G6,1),0),0) -> -75 | H12: =IFERROR(ROUND('5_P&L'!H19/IFERROR('5_P&L'!H14/'3_Demand'!H6,1),0),0) -> -78 | I12: =IFERROR(ROUND('5_P&L'!I19/IFERROR('5_P&L'!I14/'3_Demand'!I6,1),0),0) -> -82 | ... M12: =IFERROR(ROUND('5_P&L'!M19/IFERROR('5_P&L'!M14/'3_Demand'!M6,1),0),0) -> -99 | N12: =AVERAGE(B12:M12) -> -78.166667
A13: Artisan payout per order (₹) | B13: =IFERROR('3_Demand'!B8*(1-'1_Assumptions'!$B$4)/'3_Demand'!B6,0) -> 73.125 | C13: =IFERROR('3_Demand'!C8*(1-'1_Assumptions'!$B$4)/'3_Demand'!C6,0) -> 67 | D13: =IFERROR('3_Demand'!D8*(1-'1_Assumptions'!$B$4)/'3_Demand'!D6,0) -> 69 | E13: =IFERROR('3_Demand'!E8*(1-'1_Assumptions'!$B$4)/'3_Demand'!E6,0) -> 58.090909 | F13: =IFERROR('3_Demand'!F8*(1-'1_Assumptions'!$B$4)/'3_Demand'!F6,0) -> 50.538462 | G13: =IFERROR('3_Demand'!G8*(1-'1_Assumptions'!$B$4)/'3_Demand'!G6,0) -> 45 | H13: =IFERROR('3_Demand'!H8*(1-'1_Assumptions'!$B$4)/'3_Demand'!H6,0) -> 40.764706 | I13: =IFERROR('3_Demand'!I8*(1-'1_Assumptions'!$B$4)/'3_Demand'!I6,0) -> 35.55 | ... M13: =IFERROR('3_Demand'!M8*(1-'1_Assumptions'!$B$4)/'3_Demand'!M6,0) -> 22.371429 | N13: =AVERAGE(B13:M13) -> 45.525235

Sheet 7_Scenarios
A1: SCENARIO COMPARISON — CONSERVATIVE vs BASE CASE vs OPTIMISTIC
A2: Adjust inputs below, then compare outcomes. The BASE CASE uses Sheet 1 (1_Assumptions). Conservative and Optimistic use overrides below.
A3: Assumption / KPI | B3: Conservative | C3: Base Case | D3: Optimistic | E3: Notes
A4: INPUT ASSUMPTIONS
A5: Commission rate | B5: 0.08 | C5: 0.1 | D5: 0.14 | E5: Realistic floor. Low commission + low growth.
A6: Starting orders (M1) | B6: 5 | C6: ='1_Assumptions'!B4 -> 0.1 | D6: 14
A7: MoM order growth | B7: 0.08 | C7: 0.15 | D7: 0.22 | E7: Base case — uses 1_Assumptions sheet for live calcs.
A8: Starting AOV (₹) | B8: 550 | C8: 650 | D8: 800
A9: AOV monthly increment (₹) | B9: 10 | C9: 20 | D9: 30 | E9: Requires consistent social media + 1 viral moment.
A10: YEAR 1 OUTPUTS
A11: Total orders fulfilled | B11: 93 | C11: 219 | D11: 597
A12: Gross Merch Value — GMV (₹) | B12: 57070 | C12: 173330 | D12: 615180
A13: Platform Revenue (₹) | B13: 4565.6 | C13: 17333 | D13: 86125.2
A14: Total Costs (₹) | B14: 142641.4 | C14: 158566.6 | D14: 207103.6
A15: Net P&L Year 1 (₹) | B15: -138075.8 | C15: -141233.6 | D15: -120978.4
A16: Break-even month | B16: Not in Y1 | C16: Not in Y1 | D16: Not in Y1 | E16: Same regardless of scenario — fixed first trip
A17: Artisans onboarded | B17: 30 | C17: 30 | D17: 30
A18: STRATEGIC COMMENTARY
A19: Recommended action | B19: Extend runway; focus on quality\onboarding | C19: Execute as planned; review at M6 | D19: Consider adding 2nd batch artisans at M6
